README.rst
setup.py
snatch/__init__.py
snatch/api.py
snatch/events.py
snatch/models.py
snatch/scraper.py
snatch/utils.py
snatch.egg-info/PKG-INFO
snatch.egg-info/SOURCES.txt
snatch.egg-info/dependency_links.txt
snatch.egg-info/not-zip-safe
snatch.egg-info/requires.txt
snatch.egg-info/top_level.txt
test/test_snatch.py