Metadata-Version: 1.0
Name: snatch
Version: 0.1.0
Summary: Simple image scraping in Python
Home-page: https://github.com/maisano/snatch
Author: maisano
Author-email: rickmaisano@gmail.com
License: Copyright 2013 Richard Maisano
